{
  "status": {
    "timestamp": "2025-09-30T12:29:40.656346",
    "execution_time": "3 days, 0:05:51",
    "repository_status": {
      "completed": 40
    },
    "agent_swarm_status": {
      "completed": 40
    },
    "recent_heartbeats": 0,
    "model_distribution": {},
    "system_health": "operational"
  },
  "processes": {
    "global_master_orchestrator": false,
    "heartbeat_monitor": true,
    "parallel_processing_maximizer": false
  },
  "progress_percent": 100.0,
  "system_health": "degraded"
}